{
    "Pulp Fiction": {
        "rating": 9.5,
        "release": 1994
    },
    "The Room": {
        "rating": 2.0,
        "release": 1972
    },
    "The Godfather": {
        "rating": 9.2,
        "release": 1972
    },
    "The Godfather: Part II": {
        "rating": 9.0,
        "release": 1974
    },
    "The Dark Knight": {
        "rating": 9.0,
        "release": 2008
    },
    "12 Angry Men": {
        "rating": 8.9,
        "release": 1957
    },
    "Everything Everywhere All At Once": {
        "rating": 3.6,
        "release": 2022
    },
    "Forrest Gump": {
        "rating": 8.8,
        "release": 1994
    },
    "Star Wars: Episode V": {
        "rating": 8.7,
        "release": 1980
    },
    "Interstellar": {
        "rating": 10.0,
        "release": 2014
    }
}